scispacy/__init__.py
scispacy/abbreviation.py
scispacy/base_project_code.py
scispacy/candidate_generation.py
scispacy/consts.py
scispacy/custom_sentence_segmenter.py
scispacy/custom_tokenizer.py
scispacy/data_util.py
scispacy/file_cache.py
scispacy/hearst_patterns.py
scispacy/hyponym_detector.py
scispacy/linking.py
scispacy/linking_utils.py
scispacy/per_class_scorer.py
scispacy/train_utils.py
scispacy/umls_linking.py
scispacy/umls_semantic_type_tree.py
scispacy/umls_utils.py
scispacy/util.py
scispacy/version.py
scispacy_ops-0.5.4.dist-info/LICENSE
scispacy_ops-0.5.4.dist-info/METADATA
scispacy_ops-0.5.4.dist-info/WHEEL
scispacy_ops-0.5.4.dist-info/top_level.txt
scispacy_ops-0.5.4.dist-info/RECORD
