Metadata-Version: 2.1
Name: scispacy-ops
Version: 0.5.4
Summary: A full SpaCy pipeline and models for scientific/biomedical documents.
Home-page: https://allenai.github.io/scispacy/
Author: Allen Institute for Artificial Intelligence
Author-email: ai2-info@allenai.org
License: Apache
Keywords: bioinformatics nlp spacy SpaCy biomedical
Classifier: Intended Audience :: Science/Research
Classifier: Development Status :: 3 - Alpha
Classifier: License :: OSI Approved :: Apache Software License
Classifier: Programming Language :: Python :: 3.6
Classifier: Topic :: Scientific/Engineering :: Artificial Intelligence
Classifier: Topic :: Scientific/Engineering :: Bio-Informatics
Requires-Python: >=3.6.0
License-File: LICENSE
Requires-Dist: spacy <3.8.0,>=3.7.0
Requires-Dist: scipy <1.11
Requires-Dist: requests <3.0.0,>=2.0.0
Requires-Dist: conllu
Requires-Dist: numpy
Requires-Dist: joblib
Requires-Dist: nmslib-metabrainz
Requires-Dist: scikit-learn >=0.20.3
Requires-Dist: pysbd
